<?xml version="1.0" encoding="UTF-8"?>
<!DOCTYPE mapper PUBLIC "-//mybatis.org//DTD Mapper 3.0//EN" "http://mybatis.org/dtd/mybatis-3-mapper.dtd">
<mapper namespace="cn.com.clubank.weihang.manage.repair.dao.WorkCarPicMapper">
  <resultMap id="BaseResultMap" type="cn.com.clubank.weihang.manage.repair.pojo.WorkCarPic">
    <!--
      WARNING - @mbggenerated
      This element is automatically generated by MyBatis Generator, do not modify.
    -->
    <id column="csp_id" jdbcType="VARCHAR" property="cspId" />
    <result column="work_order_id" jdbcType="VARCHAR" property="workOrderId" />
    <result column="pic_url" jdbcType="VARCHAR" property="picUrl" />
    <result column="description" jdbcType="VARCHAR" property="description" />
    <result column="create_date" jdbcType="TIMESTAMP" property="createDate" />
    <result column="create_user_Id" jdbcType="VARCHAR" property="createUserId" />
    <result column="create_user_name" jdbcType="VARCHAR" property="createUserName" />
  </resultMap>
  <delete id="deleteByPrimaryKey" parameterType="java.lang.String">
    <!--
      WARNING - @mbggenerated
      This element is automatically generated by MyBatis Generator, do not modify.
    -->
    delete from work_car_pic
    where csp_id = #{cspId,jdbcType=VARCHAR}
  </delete>
  <insert id="insert" parameterType="cn.com.clubank.weihang.manage.repair.pojo.WorkCarPic">
    <!--
      WARNING - @mbggenerated
      This element is automatically generated by MyBatis Generator, do not modify.
    -->
    insert into work_car_pic (csp_id, work_order_id, pic_url, 
      description, create_date, create_user_Id, 
      create_user_name)
    values (#{cspId,jdbcType=VARCHAR}, #{workOrderId,jdbcType=VARCHAR}, #{picUrl,jdbcType=VARCHAR}, 
      #{description,jdbcType=VARCHAR}, #{createDate,jdbcType=TIMESTAMP}, #{createUserId,jdbcType=VARCHAR}, 
      #{createUserName,jdbcType=VARCHAR})
  </insert>
  <update id="updateByPrimaryKey" parameterType="cn.com.clubank.weihang.manage.repair.pojo.WorkCarPic">
    <!--
      WARNING - @mbggenerated
      This element is automatically generated by MyBatis Generator, do not modify.
    -->
    update work_car_pic
    set work_order_id = #{workOrderId,jdbcType=VARCHAR},
      pic_url = #{picUrl,jdbcType=VARCHAR},
      description = #{description,jdbcType=VARCHAR},
      create_date = #{createDate,jdbcType=TIMESTAMP},
      create_user_Id = #{createUserId,jdbcType=VARCHAR},
      create_user_name = #{createUserName,jdbcType=VARCHAR}
    where csp_id = #{cspId,jdbcType=VARCHAR}
  </update>
  <select id="selectByPrimaryKey" parameterType="java.lang.String" resultMap="BaseResultMap">
    <!--
      WARNING - @mbggenerated
      This element is automatically generated by MyBatis Generator, do not modify.
    -->
    select csp_id, work_order_id, pic_url, description, create_date, create_user_Id, 
    create_user_name
    from work_car_pic
    where csp_id = #{cspId,jdbcType=VARCHAR}
  </select>
  <select id="selectAll" resultMap="BaseResultMap">
    <!--
      WARNING - @mbggenerated
      This element is automatically generated by MyBatis Generator, do not modify.
    -->
    select csp_id, work_order_id, pic_url, description, create_date, create_user_Id, 
    create_user_name
    from work_car_pic
  </select>
  
  <!-- 通过工单ID得到图片路径 -->
  <select id="selectByWorkOrderId" parameterType="java.lang.String" resultMap="BaseResultMap">
  	select csp_id, pic_url, work_order_id
    from work_car_pic
    where work_order_id = #{workOrderId,jdbcType=VARCHAR}
  </select>
</mapper>